pyokta_aws/__init__.py
pyokta_aws/__main__.py
pyokta_aws/cli.py
pyokta_aws/exceptions.py
pyokta_aws/settings.py
pyokta_aws/utils.py
pyokta_aws/commands/__init__.py
pyokta_aws/commands/auth.py
pyokta_aws/commands/configure.py
pyokta_aws/okta/__init__.py
pyokta_aws/okta/api.py
pyokta_aws_cli_assume_role-0.3.0.dist-info/LICENSE
pyokta_aws_cli_assume_role-0.3.0.dist-info/METADATA
pyokta_aws_cli_assume_role-0.3.0.dist-info/WHEEL
pyokta_aws_cli_assume_role-0.3.0.dist-info/entry_points.txt
pyokta_aws_cli_assume_role-0.3.0.dist-info/top_level.txt
pyokta_aws_cli_assume_role-0.3.0.dist-info/RECORD
