Metadata-Version: 2.1
Name: pyokta-aws-cli-assume-role
Version: 0.3.0
Summary: AWS cli assume role and Okta authentication.
Home-page: https://github.com/mijdavis2/pyokta-aws-cli-assume-role/
Author: mijdavis2
Author-email: no_reply@example.com
License: UNKNOWN
Platform: UNKNOWN
Classifier: Programming Language :: Python :: 3
Classifier: License :: OSI Approved :: GNU General Public License v3 (GPLv3)
Requires-Python: >=3.5
Requires-Dist: boto3 (>=1.9)
Requires-Dist: configobj (>=5.0)
Requires-Dist: pyquery (>=1.4)
Requires-Dist: requests (>=2.22)
Requires-Dist: pkginfo (>=1.5)
Requires-Dist: setuptools
